server.py
mseep_unitree_go2_mcp_server-0.1.1.dist-info/licenses/LICENSE
mseep_unitree_go2_mcp_server-0.1.1.dist-info/METADATA
mseep_unitree_go2_mcp_server-0.1.1.dist-info/WHEEL
mseep_unitree_go2_mcp_server-0.1.1.dist-info/entry_points.txt
mseep_unitree_go2_mcp_server-0.1.1.dist-info/top_level.txt
mseep_unitree_go2_mcp_server-0.1.1.dist-info/RECORD
