Metadata-Version: 2.4
Name: mseep-unitree-go2-mcp-server
Version: 0.1.1
Summary: The Unitree Go2 MCP Server is a server built on the MCP that enables users to control the Unitree Go2 robot using natural language commands interpreted by a LLM.
Author-email: mseep <support@skydeck.ai>
Requires-Python: >=3.10
License-File: LICENSE
Requires-Dist: mcp>=1.7.1
Requires-Dist: websocket>=0.2.1
Dynamic: license-file
